AUTHORS.rst
LICENSE
MANIFEST.in
README.rst
setup.py
django_lot.egg-info/PKG-INFO
django_lot.egg-info/SOURCES.txt
django_lot.egg-info/dependency_links.txt
django_lot.egg-info/not-zip-safe
django_lot.egg-info/requires.txt
django_lot.egg-info/top_level.txt
lot/__init__.py
lot/admin.py
lot/auth_backend.py
lot/middleware.py
lot/models.py
lot/urls.py
lot/views.py
lot/migrations/0001_initial.py
lot/migrations/0002_lot_next_url.py
lot/migrations/__init__.py