Metadata-Version: 1.1
Name: django-lot
Version: 0.0.6
Summary: Django Login over Token.
Home-page: https://github.com/jespino/django-lot
Author: Jesús Espino, Curtis Malone
Author-email: jespinog@gmail.com, curtis@tinbrain.net
License: UNKNOWN
Platform: UNKNOWN
Classifier: Development Status :: 5 - Production/Stable
Classifier: Programming Language :: Python
Classifier: Operating System :: OS Independent
Classifier: Topic :: Software Development :: Libraries
Classifier: Topic :: Utilities
Classifier: Environment :: Web Environment
Classifier: Framework :: Django
